sirius_jz
