Metadata-Version: 2.1
Name: sirius-jz
Version: 0.0.24
Summary: Sirius Studio for development
Home-page: https://github.com/
Author: LUIZ GUILHERME C S PADUA
Author-email: jzguipadua@gmail.com
License: MIT
Project-URL: Código fonte, https://github.com/
Project-URL: Download, https://github.com/
Keywords: JackZafira Sirius Studio si Bifrost
Platform: UNKNOWN
Classifier: Development Status :: 1 - Planning
Classifier: Intended Audience :: Developers
Classifier: License :: OSI Approved :: MIT License
Classifier: Natural Language :: Portuguese (Brazilian)
Classifier: Operating System :: OS Independent
Classifier: Topic :: Software Development :: Internationalization
License-File: LICENSE.txt
